Rps/Match.py
Rps/RpsCore.py
Rps/__init__.py
Rps/Types/Card.py
Rps/Types/Player.py
Rps/Types/__init__.py
PyRps-0.1.1.dist-info/LICENSE
PyRps-0.1.1.dist-info/METADATA
PyRps-0.1.1.dist-info/WHEEL
PyRps-0.1.1.dist-info/top_level.txt
PyRps-0.1.1.dist-info/RECORD
