Metadata-Version: 2.1
Name: PyRps
Version: 0.1.1
Summary: A gaming package for python
Home-page: https://github.com/immmdreza/PyRps
Author: immmdreza
Author-email: ir310022@gmail.com
License: UNKNOWN
Project-URL: Bug Tracker, https://github.com/immmdreza/PyRps/issues
Platform: UNKNOWN
Classifier: Programming Language :: Python :: 3
Classifier: License :: OSI Approved :: MIT License
Classifier: Operating System :: OS Independent
Requires-Python: >=3.6
